{"times":[0,6339.622641509433,12679.245283018867,19018.867924528302,25358.490566037734,31698.113207547172,38037.735849056604,44377.35849056604,50716.98113207547,57056.6037735849,63396.226415094345,69735.84905660378,76075.47169811321,82415.09433962264,88754.71698113208,95094.3396226415,101433.96226415093,107773.58490566038,114113.2075471698,120452.83018867923,126792.45283018869,133132.07547169813,139471.69811320756,145811.320754717,152150.94339622642,158490.56603773584,164830.18867924527,171169.81132075473,177509.43396226416,183849.05660377358,190188.679245283,196528.30188679244,202867.92452830187,209207.54716981133,215547.16981132075,221886.79245283018,228226.4150943396,234566.03773584904,240905.66037735846,247245.2830188679,253584.90566037738,259924.5283018868,266264.15094339626,272603.77358490566,278943.3962264151,285283.0188679245,291622.641509434,297962.26415094343,304301.88679245283,310641.5094339623,316981.1320754717,323320.75471698114,329660.37735849054],"lyrics":[[{"chord":"G","text":"君","ruby":"きみ"},{"text":" "},{"text":"ー"},{"text":""}],[{"text":"それは"},{"text":"予想通","ruby":"よそうどお"},{"text":" "},{"text":"り"},{"text":""}],[{"text":"いざ"},{"text":"始","ruby":"はじ"},{"text":"まればひとり"},{"text":"芝居","ruby":"しばい"},{"text":" "},{"text":"だ"},{"text":""}],[{"text":"ずっとそばにいたって"}],[{"text":"結局","ruby":"けっきょく"},{"text":"ただの"},{"text":"観客","ruby":"かんきゃく"},{"text":"だ"}],[{"text":"感情","ruby":"かんじょう"},{"text":"ー"}],[{"text":"それはいつも"},{"text":"通","ruby":"どお"},{"text":"り"}],[{"text":"慣","ruby":"な"},{"text":"れてしまえば"},{"text":"悪","ruby":"わる"},{"text":"ど"}],[{"text":"君","ruby":"きみ"},{"text":"との ロマンス は"},{"text":"人生","ruby":"じんせい"},{"text":"柄","ruby":"がら"},{"text":""}],[{"text":"続","ruby":"つづ"},{"text":"きはしないこと を"},{"text":"知","ruby":"し"},{"text":"た"}],[{"text":"もっと"},{"text":"違","ruby":"ちが"},{"text":"う"},{"text":"設定","ruby":"せってい"},{"text":"で もっと"},{"text":"違","ruby":"ちが"},{"text":"う"},{"text":"関係","ruby":"かんけい"},{"text":"で"}],[{"text":"出会","ruby":"であ"},{"text":"える"},{"text":"世界線","ruby":"せかいせん"},{"text":"選","ruby":"えら"},{"text":"た"}],[{"text":"もっと"},{"text":"違","ruby":"ちが"},{"text":"う"},{"text":"性格","ruby":"せいかく"},{"text":"で もっと"},{"text":"違","ruby":"ちが"},{"text":"う"},{"text":"価値観","ruby":"かちかん"},{"text":"で"}],[{"text":"愛","ruby":"あい"},{"text":"を"},{"text":"伝","ruby":"つた"},{"text":"えられたらいいな そうO"},{"text":"願","ruby":"ねが"},{"text":"っても"},{"text":"無駄","ruby":"むだ"},{"text":"ら"}],[{"text":"グッバイ"}],[{"text":"君","ruby":"きみ"},{"text":"の"},{"text":"運命","ruby":"うんめい"},{"text":"の ヒト は"},{"text":"僕","ruby":"ぼく"},{"text":"い"}],[{"text":"辛","ruby":"つら"},{"text":"いけど"},{"text":"否","ruby":"いな"},{"text":"めない でも"},{"text":"離","ruby":"はな"},{"text":"れ"},{"text":"難","ruby":"がた"},{"text":"さ"}],[{"text":"その"},{"text":"髪","ruby":"かみ"},{"text":"に"},{"text":"触","ruby":"ふ"},{"text":"れただけで"},{"text":"痛","ruby":"いた"},{"text":"や"}],[{"text":"いやでも"},{"text":"甘","ruby":"あま"},{"text":"や"}],[{"text":"グッバイ"}],[{"text":"それじゃ"},{"text":"僕","ruby":"ぼく"},{"text":"にとって"},{"text":"君","ruby":"きみ"},{"text":"は"},{"text":"何","ruby":"なに"},{"text":"？"}],[{"text":"答","ruby":"こた"},{"text":"えは"},{"text":"分","ruby":"わ"},{"text":"からない"},{"text":"分","ruby":"わ"},{"text":"さ"}],[{"text":"たったひとつ"},{"text":"確","ruby":"たし"},{"text":"ば"}],[{"text":"「"},{"text":"君","ruby":"きみ"},{"text":"は"},{"text":"綺麗","ruby":"きれい"},{"text":"」"}],[{"text":"誰","ruby":"だれ"},{"text":"かが"},{"text":"偉","ruby":"えら"},{"text":"に"}],[{"text":"語","ruby":"かた"},{"text":"る"},{"text":"恋愛","ruby":"れんあい"},{"text":"の"},{"text":"論理","ruby":"ろんり"},{"text":""}],[{"text":"何","ruby":"なに"},{"text":"て"}],[{"text":"飛行機","ruby":"ひこうき"},{"text":"の"},{"text":"窓","ruby":"まど"},{"text":"から"},{"text":"見下","ruby":"みお"},{"text":"た"}],[{"text":"知","ruby":"し"},{"text":"らない"},{"text":"街","ruby":"まち"},{"text":"の"},{"text":"夜景","ruby":"やけい"},{"text":"だ"}],[{"text":"もっと"},{"text":"違","ruby":"ちが"},{"text":"う"},{"text":"設定","ruby":"せってい"},{"text":"で もっと"},{"text":"違","ruby":"ちが"},{"text":"う"},{"text":"関係","ruby":"かんけい"},{"text":"で"}],[{"text":"出会","ruby":"であ"},{"text":"える"},{"text":"世界線","ruby":"せかいせん"},{"text":"選","ruby":"えら"},{"text":"た"}],[{"text":"いたって"},{"text":"純","ruby":"じゅん"},{"text":"な"},{"text":"心","ruby":"こころ"},{"text":"で"}],[{"text":"叶","ruby":"かな"},{"text":"った"},{"text":"恋","ruby":"こい"},{"text":"を"},{"text":"抱","ruby":"だ"},{"text":"て"}],[{"text":"「"},{"text":"好","ruby":"す"},{"text":"きだ」とか"},{"text":"無責任","ruby":"むせきにん"},{"text":"に"},{"text":"言","ruby":"い"},{"text":"な"}],[{"text":"そう"},{"text":"願","ruby":"ねが"},{"text":"っても"},{"text":"虚","ruby":"むな"},{"text":"さ"}],[{"text":"グッバイ"}],[{"text":"繋","ruby":"つな"},{"text":"いだ"},{"text":"手","ruby":"て"},{"text":"の"},{"text":"向","ruby":"む"},{"text":"ン"}],[{"text":"引","ruby":"び"},{"text":"き"},{"text":"伸","ruby":"の"},{"text":"ばすたびに"},{"text":"疼","ruby":"うず"},{"text":"きだす"},{"text":"未来","ruby":"みらい"},{"text":"は"}],[{"text":"君","ruby":"きみ"},{"text":"はいない その"},{"text":"事実","ruby":"じじつ"},{"text":"."}],[{"text":"そりゃ"},{"text":"苦","ruby":"くる"},{"text":"な"}],[{"text":"グッバイ"}],[{"text":"君","ruby":"きみ"},{"text":"の"},{"text":"運命","ruby":"うんめい"},{"text":"の ヒト は"},{"text":"僕","ruby":"ぼく"},{"text":"い"}],[{"text":"辛","ruby":"つら"},{"text":"いけど"},{"text":"否","ruby":"いな"},{"text":"めない でも"},{"text":"離","ruby":"はな"},{"text":"れ"},{"text":"難","ruby":"がた"},{"text":"さ"}],[{"text":"その"},{"text":"髪","ruby":"かみ"},{"text":"に"},{"text":"触","ruby":"ふ"},{"text":"れただけで"},{"text":"痛","ruby":"いた"},{"text":"や"}],[{"text":"いやでも"},{"text":"甘","ruby":"あま"},{"text":"や"}],[{"text":"グッバイ"}],[{"text":"それじゃ"},{"text":"僕","ruby":"ぼく"},{"text":"にとって"},{"text":"君","ruby":"きみ"},{"text":"は"},{"text":"何","ruby":"なに"},{"text":"？"}],[{"text":"答","ruby":"こた"},{"text":"えは"},{"text":"分","ruby":"わ"},{"text":"からない"},{"text":"分","ruby":"わ"},{"text":"さ"}],[{"text":"たったひとつ"},{"text":"確","ruby":"たし"},{"text":"ば"}],[{"text":"「"},{"text":"君","ruby":"きみ"},{"text":"は"},{"text":"綺麗","ruby":"きれい"},{"text":"」"}],[{"text":"それもこれも ロマンス の"},{"text":"定","ruby":"さだ"},{"text":"めなら"},{"text":"悪","ruby":"わる"},{"text":"な"}],[{"text":"永遠","ruby":"えいえん"},{"text":"も"},{"text":"約束","ruby":"やくそく"},{"text":"ど"}],[{"text":"「とても"},{"text":"綺麗","ruby":"きれい"},{"text":"」"}]]}